sony_camera_remote_sdk_rest_api_client/__init__.py
sony_camera_remote_sdk_rest_api_client/api/__init__.py
sony_camera_remote_sdk_rest_api_client/api/actions/__init__.py
sony_camera_remote_sdk_rest_api_client/api/actions/execute_action.py
sony_camera_remote_sdk_rest_api_client/api/connection/__init__.py
sony_camera_remote_sdk_rest_api_client/api/connection/connect_camera.py
sony_camera_remote_sdk_rest_api_client/api/connection/disconnect_camera.py
sony_camera_remote_sdk_rest_api_client/api/connection/get_connection_status.py
sony_camera_remote_sdk_rest_api_client/api/discovery/__init__.py
sony_camera_remote_sdk_rest_api_client/api/discovery/list_cameras.py
sony_camera_remote_sdk_rest_api_client/api/live_view/__init__.py
sony_camera_remote_sdk_rest_api_client/api/live_view/start_live_view.py
sony_camera_remote_sdk_rest_api_client/api/live_view/stop_live_view.py
sony_camera_remote_sdk_rest_api_client/api/properties/__init__.py
sony_camera_remote_sdk_rest_api_client/api/properties/get_all_properties.py
sony_camera_remote_sdk_rest_api_client/api/properties/get_property.py
sony_camera_remote_sdk_rest_api_client/api/properties/set_property.py
sony_camera_remote_sdk_rest_api_client/api/sd_card/__init__.py
sony_camera_remote_sdk_rest_api_client/api/sd_card/download_sd_card_file.py
sony_camera_remote_sdk_rest_api_client/api/sd_card/list_sd_card_files.py
sony_camera_remote_sdk_rest_api_client/api/settings/__init__.py
sony_camera_remote_sdk_rest_api_client/api/settings/download_camera_settings.py
sony_camera_remote_sdk_rest_api_client/api/settings/list_camera_settings.py
sony_camera_remote_sdk_rest_api_client/api/settings/upload_camera_settings.py
sony_camera_remote_sdk_rest_api_client/client.py
sony_camera_remote_sdk_rest_api_client/errors.py
sony_camera_remote_sdk_rest_api_client/models/__init__.py
sony_camera_remote_sdk_rest_api_client/models/api_response.py
sony_camera_remote_sdk_rest_api_client/models/camera_info.py
sony_camera_remote_sdk_rest_api_client-2.1.0.dist-info/METADATA
sony_camera_remote_sdk_rest_api_client-2.1.0.dist-info/WHEEL
sony_camera_remote_sdk_rest_api_client-2.1.0.dist-info/RECORD
